cp32.py
cp32-1.0.0.dist-info/LICENSE
cp32-1.0.0.dist-info/METADATA
cp32-1.0.0.dist-info/WHEEL
cp32-1.0.0.dist-info/top_level.txt
cp32-1.0.0.dist-info/RECORD
