Metadata-Version: 2.1
Name: cp32
Version: 1.0.0
Summary: simple cipher
Home-page: https://github.com/wew1234GD/32BitCipher
Author: wew1234GD
Author-email: candyfoxowo28@gmail.com
License: MIT
Platform: UNKNOWN
Classifier: Programming Language :: Python :: 3
Classifier: License :: OSI Approved :: MIT License
Classifier: Operating System :: OS Independent
Requires-Python: >=3.6
License-File: LICENSE
